clip_api_service-0.1.3.dist-info/METADATA
clip_api_service-0.1.3.dist-info/WHEEL
clip_api_service-0.1.3.dist-info/entry_points.txt
clip_api_service-0.1.3.dist-info/licenses/LICENSE
clip_api_service/__about__.py
clip_api_service/__init__.py
clip_api_service/_service.py
clip_api_service/bentofiles/bentofile.openai.cpu.yaml
clip_api_service/bentofiles/bentofile.openai.gpu.yaml
clip_api_service/bentofiles/bentofile.openclip.cpu.yaml
clip_api_service/bentofiles/bentofile.openclip.gpu.yaml
clip_api_service/build.py
clip_api_service/cli.py
clip_api_service/models/__init__.py
clip_api_service/models/cclip.py
clip_api_service/models/mclip.py
clip_api_service/models/openai.py
clip_api_service/models/openclip.py
clip_api_service/runners.py
clip_api_service/samples.py
clip_api_service/utils.py
clip_api_service-0.1.3.dist-info/RECORD
