Metadata-Version: 2.1
Name: CLIP-API-service
Version: 0.1.3
Summary: Build AI applications with any CLIP models - embed image and sentences, object recognition, visual reasoning, image classification and reverse image search
Keywords: CLIP BentoML Model-Inference image-search object-detection visual-reasoning image-classification transformers artificial-intelligence machine-learning
Author-Email: BentoML Authors <contact@bentoml.com>
License: Apache-2.0
Classifier: Programming Language :: Python :: 3
Classifier: License :: OSI Approved :: Apache Software License
Classifier: Operating System :: OS Independent
Project-URL: Homepage, https://github.com/bentoml/CLIP-API-service
Project-URL: Bug tracker, https://github.com/bentoml/CLIP-API-service/issues
Requires-Python: >=3.8
Requires-Dist: bentoml>=1.0.20
Requires-Dist: bentoml
Requires-Dist: transformers
Requires-Dist: accelerate
Requires-Dist: optimum
Requires-Dist: pydantic>=2.0.0
Requires-Dist: Pillow
Requires-Dist: open-clip-torch
Requires-Dist: torch==2.0.0
Requires-Dist: typer
